<?xml version="1.0" encoding="US-ASCII" standalone="yes"?><?mso-application progid="Excel.Sheet"?><Workbook xmlns="urn:schemas-microsoft-com:office:spreadsheet" xmlns:o="urn:schemas-microsoft-com:office:office" xmlns:x="urn:schemas-microsoft-com:office:excel" xmlns:ss="urn:schemas-microsoft-com:office:spreadsheet" xmlns:html="http://www.w3.org/TR/REC-html40"><DocumentProperties xmlns="urn:schemas-microsoft-com:office:office"><Author></Author><LastAuthor></LastAuthor><Created></Created><LastSaved></LastSaved><Company></Company><Version></Version></DocumentProperties><ExcelWorkbook  xmlns="urn:schemas-microsoft-com:office:excel"><ProtectStructure>False</ProtectStructure><ProtectWindows>False</ProtectWindows></ExcelWorkbook><Styles><Style ss:ID="Default" ss:Name="Normal"><Alignment ss:Vertical="Bottom"/><Borders/><Font ss:FontName="Calibri" ss:Size="10"/><Interior/><NumberFormat/><Protection/></Style><Style ss:ID="s1"><Font ss:FontName="Calibri" ss:Bold="1" ss:Size="12"/><NumberFormat/></Style><Style ss:ID="s21"><Alignment ss:Horizontal="Center" ss:Vertical="Bottom"/><NumberFormat/><Font ss:FontName="Calibri" ss:Size="10"/><Borders><Border ss:Position="Top" ss:LineStyle="Continuous" ss:Weight="1"/></Borders></Style><Style ss:ID="s22"><Alignment ss:Horizontal="Center" ss:Vertical="Bottom"/><Font ss:FontName="Calibri" ss:Size="10"/><NumberFormat/></Style><Style ss:ID="s23"><Alignment ss:Horizontal="Center" ss:Vertical="Bottom"/><NumberFormat/><Font ss:FontName="Calibri" ss:Size="10"/><Borders><Border ss:Position="Bottom" ss:LineStyle="Continuous" ss:Weight="1"/></Borders></Style><Style ss:ID="s24"><Font ss:FontName="Calibri" ss:Size="10"/><NumberFormat/></Style><Style ss:ID="s31"><Font ss:FontName="Calibri" ss:Size="10"/><Borders><Border ss:Position="Top" ss:LineStyle="Continuous" ss:Weight="1"/></Borders></Style><Style ss:ID="s32"><Font ss:FontName="Calibri" ss:Size="10"/><Borders/></Style><Style ss:ID="s33"><Font ss:FontName="Calibri" ss:Size="10"/><Borders><Border ss:Position="Bottom" ss:LineStyle="Continuous" ss:Weight="1"/></Borders></Style></Styles><Names></Names><Worksheet ss:Name="Sheet1"><Table ss:ExpandedColumnCount="4" ss:ExpandedRowCount="47" x:FullColumns="1" x:FullRows="1"><Column ss:AutoFitWidth="0" ss:Width="72"/><Column ss:AutoFitWidth="0" ss:Width="58"/><Column ss:AutoFitWidth="0" ss:Width="58"/><Column ss:AutoFitWidth="0" ss:Width="58"/><Row></Row><Row><Cell ss:StyleID="s31"><Data ss:Type="String"></Data></Cell><Cell ss:StyleID="s21"><Data ss:Type="String">(1)</Data></Cell><Cell ss:StyleID="s21"><Data ss:Type="String">(2)</Data></Cell><Cell ss:StyleID="s21"><Data ss:Type="String">(3)</Data></Cell></Row><Row><Cell ss:StyleID="s32"><Data ss:Type="String">VARIABLES</Data></Cell><Cell ss:StyleID="s22"><Data ss:Type="String">SYS-GMM1.1</Data></Cell><Cell ss:StyleID="s22"><Data ss:Type="String">SYS-GMM1.2</Data></Cell><Cell ss:StyleID="s22"><Data ss:Type="String">SYS-GMM1.3</Data></Cell></Row><Row><Cell ss:StyleID="s31"><Data ss:Type="String"></Data></Cell><Cell ss:StyleID="s21"><Data ss:Type="String"></Data></Cell><Cell ss:StyleID="s21"><Data ss:Type="String"></Data></Cell><Cell ss:StyleID="s21"><Data ss:Type="String"></Data></Cell></Row><Row><Cell ss:StyleID="s32"><Data ss:Type="String">L.fdi_a</Data></Cell><Cell ss:StyleID="s22"><Data ss:Type="String">0.594***</Data></Cell><Cell ss:StyleID="s22"><Data ss:Type="String"></Data></Cell><Cell ss:StyleID="s22"><Data ss:Type="String"></Data></Cell></Row><Row><Cell ss:StyleID="s32"><Data ss:Type="String"></Data></Cell><Cell ss:StyleID="s22"><Data ss:Type="String">(0.042)</Data></Cell><Cell ss:StyleID="s22"><Data ss:Type="String"></Data></Cell><Cell ss:StyleID="s22"><Data ss:Type="String"></Data></Cell></Row><Row><Cell ss:StyleID="s32"><Data ss:Type="String">lso2</Data></Cell><Cell ss:StyleID="s22"><Data ss:Type="String">2154504.055*</Data></Cell><Cell ss:StyleID="s22"><Data ss:Type="String">-561,245.348</Data></Cell><Cell ss:StyleID="s22"><Data ss:Type="String">5119140.857***</Data></Cell></Row><Row><Cell ss:StyleID="s32"><Data ss:Type="String"></Data></Cell><Cell ss:StyleID="s22"><Data ss:Type="String">(1298723.303)</Data></Cell><Cell ss:StyleID="s22"><Data ss:Type="String">(562,526.404)</Data></Cell><Cell ss:StyleID="s22"><Data ss:Type="String">(1382929.547)</Data></Cell></Row><Row><Cell ss:StyleID="s32"><Data ss:Type="String">L.lso2</Data></Cell><Cell ss:StyleID="s22"><Data ss:Type="String">-461,948.747</Data></Cell><Cell ss:StyleID="s22"><Data ss:Type="String">277,117.176</Data></Cell><Cell ss:StyleID="s22"><Data ss:Type="String">-291,843.221</Data></Cell></Row><Row><Cell ss:StyleID="s32"><Data ss:Type="String"></Data></Cell><Cell ss:StyleID="s22"><Data ss:Type="String">(758,485.306)</Data></Cell><Cell ss:StyleID="s22"><Data ss:Type="String">(344,285.949)</Data></Cell><Cell ss:StyleID="s22"><Data ss:Type="String">(1396553.565)</Data></Cell></Row><Row><Cell ss:StyleID="s32"><Data ss:Type="String">gov_a</Data></Cell><Cell ss:StyleID="s22"><Data ss:Type="String">-43.141</Data></Cell><Cell ss:StyleID="s22"><Data ss:Type="String">418.776***</Data></Cell><Cell ss:StyleID="s22"><Data ss:Type="String">3,562.605***</Data></Cell></Row><Row><Cell ss:StyleID="s32"><Data ss:Type="String"></Data></Cell><Cell ss:StyleID="s22"><Data ss:Type="String">(287.486)</Data></Cell><Cell ss:StyleID="s22"><Data ss:Type="String">(66.009)</Data></Cell><Cell ss:StyleID="s22"><Data ss:Type="String">(491.879)</Data></Cell></Row><Row><Cell ss:StyleID="s32"><Data ss:Type="String">L.gov_a</Data></Cell><Cell ss:StyleID="s22"><Data ss:Type="String">1266312.013**</Data></Cell><Cell ss:StyleID="s22"><Data ss:Type="String">274,360.377***</Data></Cell><Cell ss:StyleID="s22"><Data ss:Type="String">2013628.093***</Data></Cell></Row><Row><Cell ss:StyleID="s32"><Data ss:Type="String"></Data></Cell><Cell ss:StyleID="s22"><Data ss:Type="String">(531,853.908)</Data></Cell><Cell ss:StyleID="s22"><Data ss:Type="String">(84,166.767)</Data></Cell><Cell ss:StyleID="s22"><Data ss:Type="String">(747,061.818)</Data></Cell></Row><Row><Cell ss:StyleID="s32"><Data ss:Type="String">secgrp_a</Data></Cell><Cell ss:StyleID="s22"><Data ss:Type="String">-26,816.927</Data></Cell><Cell ss:StyleID="s22"><Data ss:Type="String">-48,970.775**</Data></Cell><Cell ss:StyleID="s22"><Data ss:Type="String">-164,554.742</Data></Cell></Row><Row><Cell ss:StyleID="s32"><Data ss:Type="String"></Data></Cell><Cell ss:StyleID="s22"><Data ss:Type="String">(62,682.770)</Data></Cell><Cell ss:StyleID="s22"><Data ss:Type="String">(20,279.013)</Data></Cell><Cell ss:StyleID="s22"><Data ss:Type="String">(112,947.042)</Data></Cell></Row><Row><Cell ss:StyleID="s32"><Data ss:Type="String">pgrp_a</Data></Cell><Cell ss:StyleID="s22"><Data ss:Type="String">50.657***</Data></Cell><Cell ss:StyleID="s22"><Data ss:Type="String">9.299**</Data></Cell><Cell ss:StyleID="s22"><Data ss:Type="String">51.383***</Data></Cell></Row><Row><Cell ss:StyleID="s32"><Data ss:Type="String"></Data></Cell><Cell ss:StyleID="s22"><Data ss:Type="String">(14.176)</Data></Cell><Cell ss:StyleID="s22"><Data ss:Type="String">(4.268)</Data></Cell><Cell ss:StyleID="s22"><Data ss:Type="String">(13.423)</Data></Cell></Row><Row><Cell ss:StyleID="s32"><Data ss:Type="String">wage_a</Data></Cell><Cell ss:StyleID="s22"><Data ss:Type="String">-0.306***</Data></Cell><Cell ss:StyleID="s22"><Data ss:Type="String">0.250***</Data></Cell><Cell ss:StyleID="s22"><Data ss:Type="String">-0.288***</Data></Cell></Row><Row><Cell ss:StyleID="s32"><Data ss:Type="String"></Data></Cell><Cell ss:StyleID="s22"><Data ss:Type="String">(0.036)</Data></Cell><Cell ss:StyleID="s22"><Data ss:Type="String">(0.047)</Data></Cell><Cell ss:StyleID="s22"><Data ss:Type="String">(0.066)</Data></Cell></Row><Row><Cell ss:StyleID="s32"><Data ss:Type="String">laborinsec_a</Data></Cell><Cell ss:StyleID="s22"><Data ss:Type="String">291,145.883***</Data></Cell><Cell ss:StyleID="s22"><Data ss:Type="String">128,956.694***</Data></Cell><Cell ss:StyleID="s22"><Data ss:Type="String">773,553.029***</Data></Cell></Row><Row><Cell ss:StyleID="s32"><Data ss:Type="String"></Data></Cell><Cell ss:StyleID="s22"><Data ss:Type="String">(102,573.426)</Data></Cell><Cell ss:StyleID="s22"><Data ss:Type="String">(48,467.935)</Data></Cell><Cell ss:StyleID="s22"><Data ss:Type="String">(123,245.706)</Data></Cell></Row><Row><Cell ss:StyleID="s32"><Data ss:Type="String">delivery</Data></Cell><Cell ss:StyleID="s22"><Data ss:Type="String">76.919**</Data></Cell><Cell ss:StyleID="s22"><Data ss:Type="String">11.368*</Data></Cell><Cell ss:StyleID="s22"><Data ss:Type="String">165.467***</Data></Cell></Row><Row><Cell ss:StyleID="s32"><Data ss:Type="String"></Data></Cell><Cell ss:StyleID="s22"><Data ss:Type="String">(38.581)</Data></Cell><Cell ss:StyleID="s22"><Data ss:Type="String">(6.131)</Data></Cell><Cell ss:StyleID="s22"><Data ss:Type="String">(50.060)</Data></Cell></Row><Row><Cell ss:StyleID="s32"><Data ss:Type="String">density_a</Data></Cell><Cell ss:StyleID="s22"><Data ss:Type="String">33,454.353***</Data></Cell><Cell ss:StyleID="s22"><Data ss:Type="String">2,835.673</Data></Cell><Cell ss:StyleID="s22"><Data ss:Type="String">49,508.112**</Data></Cell></Row><Row><Cell ss:StyleID="s32"><Data ss:Type="String"></Data></Cell><Cell ss:StyleID="s22"><Data ss:Type="String">(11,431.943)</Data></Cell><Cell ss:StyleID="s22"><Data ss:Type="String">(4,636.925)</Data></Cell><Cell ss:StyleID="s22"><Data ss:Type="String">(23,924.026)</Data></Cell></Row><Row><Cell ss:StyleID="s32"><Data ss:Type="String">laborval</Data></Cell><Cell ss:StyleID="s22"><Data ss:Type="String">-474,394.195***</Data></Cell><Cell ss:StyleID="s22"><Data ss:Type="String">-73,268.042</Data></Cell><Cell ss:StyleID="s22"><Data ss:Type="String">-351,068.811</Data></Cell></Row><Row><Cell ss:StyleID="s32"><Data ss:Type="String"></Data></Cell><Cell ss:StyleID="s22"><Data ss:Type="String">(181,424.027)</Data></Cell><Cell ss:StyleID="s22"><Data ss:Type="String">(57,699.188)</Data></Cell><Cell ss:StyleID="s22"><Data ss:Type="String">(301,672.054)</Data></Cell></Row><Row><Cell ss:StyleID="s32"><Data ss:Type="String">L.HMT_a</Data></Cell><Cell ss:StyleID="s22"><Data ss:Type="String"></Data></Cell><Cell ss:StyleID="s22"><Data ss:Type="String">0.440***</Data></Cell><Cell ss:StyleID="s22"><Data ss:Type="String"></Data></Cell></Row><Row><Cell ss:StyleID="s32"><Data ss:Type="String"></Data></Cell><Cell ss:StyleID="s22"><Data ss:Type="String"></Data></Cell><Cell ss:StyleID="s22"><Data ss:Type="String">(0.039)</Data></Cell><Cell ss:StyleID="s22"><Data ss:Type="String"></Data></Cell></Row><Row><Cell ss:StyleID="s32"><Data ss:Type="String">L.domestic_a</Data></Cell><Cell ss:StyleID="s22"><Data ss:Type="String"></Data></Cell><Cell ss:StyleID="s22"><Data ss:Type="String"></Data></Cell><Cell ss:StyleID="s22"><Data ss:Type="String">0.494***</Data></Cell></Row><Row><Cell ss:StyleID="s32"><Data ss:Type="String"></Data></Cell><Cell ss:StyleID="s22"><Data ss:Type="String"></Data></Cell><Cell ss:StyleID="s22"><Data ss:Type="String"></Data></Cell><Cell ss:StyleID="s22"><Data ss:Type="String">(0.058)</Data></Cell></Row><Row><Cell ss:StyleID="s32"><Data ss:Type="String">Constant</Data></Cell><Cell ss:StyleID="s22"><Data ss:Type="String">-3.637e+07***</Data></Cell><Cell ss:StyleID="s22"><Data ss:Type="String">-2593086.135</Data></Cell><Cell ss:StyleID="s22"><Data ss:Type="String">-8.673e+07***</Data></Cell></Row><Row><Cell ss:StyleID="s32"><Data ss:Type="String"></Data></Cell><Cell ss:StyleID="s22"><Data ss:Type="String">(11781017.426)</Data></Cell><Cell ss:StyleID="s22"><Data ss:Type="String">(3874656.399)</Data></Cell><Cell ss:StyleID="s22"><Data ss:Type="String">(18615627.428)</Data></Cell></Row><Row><Cell ss:StyleID="s32"><Data ss:Type="String"></Data></Cell><Cell ss:StyleID="s22"><Data ss:Type="String"></Data></Cell><Cell ss:StyleID="s22"><Data ss:Type="String"></Data></Cell><Cell ss:StyleID="s22"><Data ss:Type="String"></Data></Cell></Row><Row><Cell ss:StyleID="s32"><Data ss:Type="String">Number of id</Data></Cell><Cell ss:StyleID="s22"><Data ss:Type="String">261</Data></Cell><Cell ss:StyleID="s22"><Data ss:Type="String">256</Data></Cell><Cell ss:StyleID="s22"><Data ss:Type="String">261</Data></Cell></Row><Row><Cell ss:StyleID="s32"><Data ss:Type="String">ar1</Data></Cell><Cell ss:StyleID="s22"><Data ss:Type="String">-2.061</Data></Cell><Cell ss:StyleID="s22"><Data ss:Type="String">-3.800</Data></Cell><Cell ss:StyleID="s22"><Data ss:Type="String">-5.435</Data></Cell></Row><Row><Cell ss:StyleID="s32"><Data ss:Type="String">ar1p</Data></Cell><Cell ss:StyleID="s22"><Data ss:Type="String">0.0393</Data></Cell><Cell ss:StyleID="s22"><Data ss:Type="String">0.000145</Data></Cell><Cell ss:StyleID="s22"><Data ss:Type="String">5.48e-08</Data></Cell></Row><Row><Cell ss:StyleID="s32"><Data ss:Type="String">ar2</Data></Cell><Cell ss:StyleID="s22"><Data ss:Type="String">-1.436</Data></Cell><Cell ss:StyleID="s22"><Data ss:Type="String">-1.413</Data></Cell><Cell ss:StyleID="s22"><Data ss:Type="String">-0.243</Data></Cell></Row><Row><Cell ss:StyleID="s32"><Data ss:Type="String">ar2p</Data></Cell><Cell ss:StyleID="s22"><Data ss:Type="String">0.151</Data></Cell><Cell ss:StyleID="s22"><Data ss:Type="String">0.158</Data></Cell><Cell ss:StyleID="s22"><Data ss:Type="String">0.808</Data></Cell></Row><Row><Cell ss:StyleID="s32"><Data ss:Type="String">sargan</Data></Cell><Cell ss:StyleID="s22"><Data ss:Type="String">1297</Data></Cell><Cell ss:StyleID="s22"><Data ss:Type="String">844.3</Data></Cell><Cell ss:StyleID="s22"><Data ss:Type="String">960.6</Data></Cell></Row><Row><Cell ss:StyleID="s32"><Data ss:Type="String">sarganp</Data></Cell><Cell ss:StyleID="s22"><Data ss:Type="String">0</Data></Cell><Cell ss:StyleID="s22"><Data ss:Type="String">0</Data></Cell><Cell ss:StyleID="s22"><Data ss:Type="String">0</Data></Cell></Row><Row><Cell ss:StyleID="s32"><Data ss:Type="String">hansen</Data></Cell><Cell ss:StyleID="s22"><Data ss:Type="String">241.6</Data></Cell><Cell ss:StyleID="s22"><Data ss:Type="String">228.9</Data></Cell><Cell ss:StyleID="s22"><Data ss:Type="String">242.8</Data></Cell></Row><Row><Cell ss:StyleID="s32"><Data ss:Type="String">hansenp</Data></Cell><Cell ss:StyleID="s22"><Data ss:Type="String">0.121</Data></Cell><Cell ss:StyleID="s22"><Data ss:Type="String">0.277</Data></Cell><Cell ss:StyleID="s22"><Data ss:Type="String">0.111</Data></Cell></Row><Row><Cell ss:StyleID="s33"><Data ss:Type="String">N</Data></Cell><Cell ss:StyleID="s23"><Data ss:Type="String">1441</Data></Cell><Cell ss:StyleID="s23"><Data ss:Type="String">1409</Data></Cell><Cell ss:StyleID="s23"><Data ss:Type="String">1441</Data></Cell></Row><Row><Cell ss:StyleID="s24"><Data ss:Type="String">Standard errors in parentheses</Data></Cell></Row><Row><Cell ss:StyleID="s24"><Data ss:Type="String">*** p&lt;0.01, ** p&lt;0.05, * p&lt;0.1</Data></Cell></Row></Table><WorksheetOptions xmlns="urn:schemas-microsoft-com:office:excel"><ProtectedObjects>False</ProtectedObjects><ProtectedScenarios>False</ProtectedScenarios></WorksheetOptions></Worksheet></Workbook>